conf/__init__.py
conf/oneCloudTagsCheck.py
conf/settings.py
check_terraform_resource_tags-0.1.0.dist-info/METADATA
check_terraform_resource_tags-0.1.0.dist-info/WHEEL
check_terraform_resource_tags-0.1.0.dist-info/top_level.txt
check_terraform_resource_tags-0.1.0.dist-info/RECORD
