Metadata-Version: 2.1
Name: check-terraform-resource-tags
Version: 0.1.0
Requires-Dist: checkov
